netbox_swupdate/__init__.py
netbox_swupdate/admin.py
netbox_swupdate/navigation.py
netbox_swupdate/urls.py
netbox_swupdate/actions/__init__.py
netbox_swupdate/actions/get_status_deploy.py
netbox_swupdate/actions/update_deploy_status.py
netbox_swupdate/admins/__init__.py
netbox_swupdate/admins/admin_deploy.py
netbox_swupdate/admins/admin_firmware_request.py
netbox_swupdate/admins/admin_monitoring.py
netbox_swupdate/admins/admin_repository.py
netbox_swupdate/admins/admin_software.py
netbox_swupdate/api/__init__.py
netbox_swupdate/api/urls.py
netbox_swupdate/api/serializers/__init__.py
netbox_swupdate/api/serializers/deploy_serializer.py
netbox_swupdate/api/serializers/firmware_request_serializer.py
netbox_swupdate/api/serializers/monitoring_serializer.py
netbox_swupdate/api/serializers/repository_serializer.py
netbox_swupdate/api/serializers/software_serializer.py
netbox_swupdate/api/views/__init__.py
netbox_swupdate/api/views/view_deploy.py
netbox_swupdate/api/views/view_firmware_request.py
netbox_swupdate/api/views/view_monitoring.py
netbox_swupdate/api/views/view_repository.py
netbox_swupdate/api/views/view_software.py
netbox_swupdate/api/views/view_swupdate.py
netbox_swupdate/filters/__init__.py
netbox_swupdate/filters/deploy_filter.py
netbox_swupdate/filters/firmware_request_filter.py
netbox_swupdate/filters/monitoring_filter.py
netbox_swupdate/filters/repository_filter.py
netbox_swupdate/filters/software_filter.py
netbox_swupdate/forms/__init__.py
netbox_swupdate/forms/deploy_form.py
netbox_swupdate/forms/firmware_request_form.py
netbox_swupdate/forms/monitoring_form.py
netbox_swupdate/forms/repository_form.py
netbox_swupdate/forms/software_form.py
netbox_swupdate/migrations/0001_initial.py
netbox_swupdate/migrations/__init__.py
netbox_swupdate/models/__init__.py
netbox_swupdate/models/deploy.py
netbox_swupdate/models/firmware_request.py
netbox_swupdate/models/monitoring.py
netbox_swupdate/models/repository.py
netbox_swupdate/models/software.py
netbox_swupdate-0.0.1.103.dist-info/METADATA
netbox_swupdate-0.0.1.103.dist-info/WHEEL
netbox_swupdate-0.0.1.103.dist-info/top_level.txt
netbox_swupdate-0.0.1.103.dist-info/RECORD
