Metadata-Version: 2.1
Name: netbox-swupdate
Version: 0.0.1.103
Summary: NetBox plugin for SWUpdate.
Home-page: https://github.com/netbox-community/netbox-swupdate
Author: Óscar Hurtado
Author-email: ohurtadp@sens.solutions
License: MIT
Keywords: netbox,netbox-plugin,plugin
Classifier: Development Status :: 2 - Pre-Alpha
Classifier: Intended Audience :: Developers
Classifier: Natural Language :: English
Classifier: Programming Language :: Python :: 3
Classifier: Programming Language :: Python :: 3.8
Classifier: Programming Language :: Python :: 3.9
Classifier: Programming Language :: Python :: 3.10
Requires-Python: >=3.8
